Metadata-Version: 2.1
Name: aws-oidc-provider-refresher
Version: 0.3.1
Summary: refreshes thumbprints of OpenID connect providers
Home-page: https://github.com/binxio/aws-oidc-provider-refresher
Author: Mark van Holsteijn
Author-email: mark@binx.io
License: BSD
Platform: any
Classifier: Development Status :: 4 - Beta
Classifier: Environment :: Console
Classifier: Intended Audience :: Developers
Classifier: License :: OSI Approved :: BSD License
Classifier: Operating System :: POSIX
Classifier: Operating System :: MacOS
Classifier: Operating System :: Unix
Classifier: Operating System :: Microsoft :: Windows
Classifier: Programming Language :: Python
Classifier: Programming Language :: Python :: 3
Classifier: Topic :: Software Development :: Libraries :: Python Modules
License-File: LICENSE
